main.py
model/unifialarm.py
model/unifialarmcionditionlistitem.py
model/unifialarmcondition.py
model/unifialarmsource.py
model/unifialarmtrigger.py
model/unifialert.py
unifiprotectwebhookreceiver-0.1.0.dist-info/METADATA
unifiprotectwebhookreceiver-0.1.0.dist-info/WHEEL
unifiprotectwebhookreceiver-0.1.0.dist-info/top_level.txt
unifiprotectwebhookreceiver-0.1.0.dist-info/RECORD
