Metadata-Version: 2.4
Name: unifiprotectwebhookreceiver
Version: 0.1.0
Summary: Add your description here
Requires-Python: >=3.13
Requires-Dist: fastapi>=0.121.1
Requires-Dist: pillow>=12.0.0
Requires-Dist: uvicorn>=0.38.0
